sketcher/__init__.py
sketcher/__main__.py
sketcher/backend.py
sketcher/backend_base.py
sketcher/backend_pyglet.py
sketcher/backend_tk.py
sketcher/common.py
sketcher/config.py
sketcher-1.0.3.dist-info/LICENSE
sketcher-1.0.3.dist-info/METADATA
sketcher-1.0.3.dist-info/WHEEL
sketcher-1.0.3.dist-info/top_level.txt
sketcher-1.0.3.dist-info/RECORD
