Metadata-Version: 2.1
Name: sketcher
Version: 1.0.3
Summary: A processing like sketch framework for prototyping.
Home-page: https://github.com/lattay/sketcher
Author: Théo (Lattay) Cavignac
Author-email: theo.cavignac@gmail.com
License: UNKNOWN
Platform: UNKNOWN
Classifier: Programming Language :: Python :: 3
Classifier: License :: OSI Approved :: MIT License
Classifier: Operating System :: OS Independent
